isaac/__init__.py
isaac/isaac.py
isaac-0.1.1.dist-info/LICENSE
isaac-0.1.1.dist-info/METADATA
isaac-0.1.1.dist-info/WHEEL
isaac-0.1.1.dist-info/top_level.txt
isaac-0.1.1.dist-info/RECORD
